README.md
setup.py
dmsapi/__init__.py
dmsapi/config.py
dmsapi.egg-info/PKG-INFO
dmsapi.egg-info/SOURCES.txt
dmsapi.egg-info/dependency_links.txt
dmsapi.egg-info/requires.txt
dmsapi.egg-info/top_level.txt
dmsapi/api/__init__.py
dmsapi/api/base.py
dmsapi/api/extension.py
dmsapi/api/goingout.py
dmsapi/api/info.py
dmsapi/api/meal.py
dmsapi/api/music.py
dmsapi/api/stay.py
dmsapi/core/__init__.py
dmsapi/core/auth.py
dmsapi/core/session.py
dmsapi/utils/__init__.py
dmsapi/utils/auth.py
tests/__init__.py
tests/test_config.py
tests/core/__init__.py
tests/core/test_auth.py