Metadata-Version: 2.1
Name: dmsapi
Version: 0.2.2
Summary: Simple DSM-DMS API
Home-page: https://github.com/dmsapi/python
Author: moreal
Author-email: dev.moreal@gmail.com
License: UNKNOWN
Platform: UNKNOWN
Classifier: Development Status :: 3 - Alpha
Classifier: License :: OSI Approved :: MIT License
Classifier: Programming Language :: Python :: 3.7
Classifier: Topic :: Utilities
